[
  {"root": "حق", "orbit": "الأزل (Sovereign Origin)", "energy": 1.94, "insight": "ثبات الحقيقة المطلقة"},
  {"root": "ربب", "orbit": "الأزل (Sovereign Origin)", "energy": 1.92, "insight": "التربية والرعاية المستمرة"},
  {"root": "اله", "orbit": "الأزل (Sovereign Origin)", "energy": 1.94, "insight": "الوجود المطلق"},
  {"root": "علي", "orbit": "الأزل (Sovereign Origin)", "energy": 1.90, "insight": "العلو والارتقاء"},
  {"root": "عظم", "orbit": "الأزل (Sovereign Origin)", "energy": 1.86, "insight": "الجلال والعظمة"},
  {"root": "عزز", "orbit": "الأزل (Sovereign Origin)", "energy": 1.84, "insight": "القوة والمنعة"},
  {"root": "قدر", "orbit": "الأزل (Sovereign Origin)", "energy": 1.88, "insight": "تقدير الأزل"},
  {"root": "خلف", "orbit": "الأزل (Sovereign Origin)", "energy": 1.82, "insight": "الخلافة والاستخلاف"},
  {"root": "ملك", "orbit": "الأزل (Sovereign Origin)", "energy": 1.86, "insight": "الملك والملكوت"},
  {"root": "امر", "orbit": "السيادة (Sovereign Command)", "energy": 1.88, "insight": "الأمر الإلهي ونفاذ الكلمة"},
  {"root": "حكم", "orbit": "السيادة (Sovereign Command)", "energy": 1.86, "insight": "الفصل بين الحق والباطل"},
  {"root": "قضى", "orbit": "السيادة (Sovereign Command)", "energy": 1.84, "insight": "القضاء النافذ"},
  {"root": "عدل", "orbit": "السيادة (Sovereign Command)", "energy": 1.82, "insight": "العدل والاستقامة"},
  {"root": "صدق", "orbit": "السيادة (Sovereign Command)", "energy": 1.86, "insight": "مطابقة القول للواقع"},
  {"root": "قوم", "orbit": "السيادة (Sovereign Command)", "energy": 1.80, "insight": "القيام بالحق"},
  {"root": "سود", "orbit": "السيادة (Sovereign Command)", "energy": 1.78, "insight": "السيادة والريادة"},
  {"root": "ولى", "orbit": "السيادة (Sovereign Command)", "energy": 1.84, "insight": "الولاية والنصرة"},
  {"root": "نصر", "orbit": "السيادة (Sovereign Command)", "energy": 1.82, "insight": "النصر والتمكين"},
  {"root": "فتح", "orbit": "السيادة (Sovereign Command)", "energy": 1.86, "insight": "الفتح والانفراج"},
  {"root": "مكن", "orbit": "التمكين (Empowerment Structure)", "energy": 1.84, "insight": "التمكين في الأرض"},
  {"root": "بني", "orbit": "التمكين (Empowerment Structure)", "energy": 1.82, "insight": "البناء والتأسيس"},
  {"root": "رفع", "orbit": "التمكين (Empowerment Structure)", "energy": 1.80, "insight": "الرفع والارتقاء"},
  {"root": "ثبت", "orbit": "التمكين (Empowerment Structure)", "energy": 1.78, "insight": "الثبات والرسوخ"},
  {"root": "صبر", "orbit": "التمكين (Empowerment Structure)", "energy": 1.82, "insight": "الصبر والثبات"},
  {"root": "قوي", "orbit": "التمكين (Empowerment Structure)", "energy": 1.80, "insight": "صلابة البنيان"},
  {"root": "شدد", "orbit": "التمكين (Empowerment Structure)", "energy": 1.78, "insight": "تمكين الحدود"},
  {"root": "رسخ", "orbit": "التمكين (Empowerment Structure)", "energy": 1.76, "insight": "ترسيخ الأساس"},
  {"root": "وسط", "orbit": "التمكين (Empowerment Structure)", "energy": 1.74, "insight": "الوسط والاعتدال"},
  {"root": "علم", "orbit": "الوعي (Consciousness & Guidance)", "energy": 1.86, "insight": "نور الوعي المتجلي"},
  {"root": "عقل", "orbit": "الوعي (Consciousness & Guidance)", "energy": 1.82, "insight": "نور البصيرة الداخلي"},
  {"root": "فقه", "orbit": "الوعي (Consciousness & Guidance)", "energy": 1.80, "insight": "استبطان المعاني"},
  {"root": "ذكر", "orbit": "الوعي (Consciousness & Guidance)", "energy": 1.84, "insight": "استحضار الحقيقة"},
  {"root": "نظر", "orbit": "الوعي (Consciousness & Guidance)", "energy": 1.78, "insight": "رؤية الحقائق"},
  {"root": "بصر", "orbit": "الوعي (Consciousness & Guidance)", "energy": 1.80, "insight": "رؤية النور"},
  {"root": "سمع", "orbit": "الوعي (Consciousness & Guidance)", "energy": 1.78, "insight": "استقبال الحقيقة"},
  {"root": "قرأ", "orbit": "الوعي (Consciousness & Guidance)", "energy": 1.82, "insight": "استنطاق النص الإلهي"},
  {"root": "هدي", "orbit": "الوعي (Consciousness & Guidance)", "energy": 1.86, "insight": "نور المسير"},
  {"root": "رشد", "orbit": "الوعي (Consciousness & Guidance)", "energy": 1.80, "insight": "نور العقل السديد"},
  {"root": "يسر", "orbit": "اليسر (Divine Ease & Flow)", "energy": 1.86, "insight": "انسياب الخير"},
  {"root": "سلم", "orbit": "اليسر (Divine Ease & Flow)", "energy": 1.84, "insight": "طمأنينة الوجود"},
  {"root": "امن", "orbit": "اليسر (Divine Ease & Flow)", "energy": 1.82, "insight": "سكون النفس"},
  {"root": "صلح", "orbit": "اليسر (Divine Ease & Flow)", "energy": 1.80, "insight": "انسياب الصلاح"},
  {"root": "لين", "orbit": "اليسر (Divine Ease & Flow)", "energy": 1.78, "insight": "انسياب الجمال"},
  {"root": "رفق", "orbit": "اليسر (Divine Ease & Flow)", "energy": 1.76, "insight": "سعة الرحمة"},
  {"root": "هون", "orbit": "اليسر (Divine Ease & Flow)", "energy": 1.74, "insight": "انسياب الطمأنينة"},
  {"root": "سكن", "orbit": "اليسر (Divine Ease & Flow)", "energy": 1.76, "insight": "استقرار النفس"},
  {"root": "نعم", "orbit": "اليسر (Divine Ease & Flow)", "energy": 1.80, "insight": "انسياب العطاء"},
  {"root": "فضل", "orbit": "اليسر (Divine Ease & Flow)", "energy": 1.82, "insight": "زيادة الخير"},
  {"root": "خلق", "orbit": "الفطرة (Primordial Nature)", "energy": 1.86, "insight": "نشأة الوجود"},
  {"root": "فطر", "orbit": "الفطرة (Primordial Nature)", "energy": 1.84, "insight": "أصل الخلق"},
  {"root": "نشأ", "orbit": "الفطرة (Primordial Nature)", "energy": 1.80, "insight": "انبثاق الوجود"},
  {"root": "بدأ", "orbit": "الفطرة (Primordial Nature)", "energy": 1.82, "insight": "نقطة الانطلاق"},
  {"root": "صور", "orbit": "الفطرة (Primordial Nature)", "energy": 1.78, "insight": "إبداع الصور"},
  {"root": "سوى", "orbit": "الفطرة (Primordial Nature)", "energy": 1.76, "insight": "استقامة الخلق"},
  {"root": "وزن", "orbit": "الفطرة (Primordial Nature)", "energy": 1.78, "insight": "ضبط الفطرة"},
  {"root": "حسن", "orbit": "الفطرة (Primordial Nature)", "energy": 1.84, "insight": "بهاء الفطرة"},
  {"root": "طهر", "orbit": "التزكية (Purification & Filter)", "energy": 1.86, "insight": "صقل الجوهر"},
  {"root": "زكى", "orbit": "التزكية (Purification & Filter)", "energy": 1.84, "insight": "نماء النقاء"},
  {"root": "غفر", "orbit": "التزكية (Purification & Filter)", "energy": 1.82, "insight": "محو الأثر"},
  {"root": "توب", "orbit": "التزكية (Purification & Filter)", "energy": 1.80, "insight": "تطهير المسار"},
  {"root": "خنس", "orbit": "التزكية (Purification & Filter)", "energy": 1.62, "insight": "فلترة الشوائب"},
  {"root": "نقى", "orbit": "التزكية (Purification & Filter)", "energy": 1.78, "insight": "إزالة الشوائب"},
  {"root": "خلص", "orbit": "التزكية (Purification & Filter)", "energy": 1.80, "insight": "نقاء النية"},
  {"root": "حيي", "orbit": "الأزل (Sovereign Origin)", "energy": 1.92, "insight": "سر الوجود المتدفق"},
  {"root": "موت", "orbit": "الأزل (Sovereign Origin)", "energy": 1.78, "insight": "باب التطهير"},
  {"root": "بعث", "orbit": "الأزل (Sovereign Origin)", "energy": 1.80, "insight": "عودة للمصدر"},
  {"root": "جمع", "orbit": "الأزل (Sovereign Origin)", "energy": 1.80, "insight": "وحدة الوجود"},
  {"root": "فرق", "orbit": "الأزل (Sovereign Origin)", "energy": 1.76, "insight": "فصل الحق"},
  {"root": "عهد", "orbit": "السيادة (Sovereign Command)", "energy": 1.82, "insight": "رباط الوفاء"},
  {"root": "شهد", "orbit": "السيادة (Sovereign Command)", "energy": 1.82, "insight": "حضور الحق"}
]
